leafolio/__init__.py
leafolio-0.0.dist-info/LICENCE
leafolio-0.0.dist-info/METADATA
leafolio-0.0.dist-info/WHEEL
leafolio-0.0.dist-info/top_level.txt
leafolio-0.0.dist-info/RECORD
