Metadata-Version: 2.1
Name: leafolio
Version: 0.0
Summary: UNKNOWN
Home-page: https://github.com/MikeSWang/Leafolio/
Author: M S Wang
License: GPLv3
Project-URL: Source, https://github.com/MikeSWang/Leafolio/tree/master
Platform: UNKNOWN
Classifier: Programming Language :: Python :: 3
Classifier: License :: OSI Approved :: GNU General Public License v3 (GPLv3)
Classifier: Operating System :: OS Independent
Requires-Python: >=3.6
Requires-Dist: numpy
Requires-Dist: scipy
Requires-Dist: pandas
